app_package/__init__.py
app_package/streamlit_app.py
mapmod-0.0.1.dist-info/LICENSE
mapmod-0.0.1.dist-info/METADATA
mapmod-0.0.1.dist-info/WHEEL
mapmod-0.0.1.dist-info/top_level.txt
mapmod-0.0.1.dist-info/RECORD
